[
  {
    "id": "aria-required-parent",
    "title": "`[role]`s are not contained by their required parent element",
    "description": "Some ARIA child roles must be contained by specific parent roles to properly perform their intended accessibility functions. [Learn more](https://web.dev/aria-required-parent/).",
    "score": 0,
    "scoreDisplayMode": "binary",
    "details": {
      "type": "table",
      "headings": [
        {
          "key": "node",
          "itemType": "node",
          "subItemsHeading": {
            "key": "relatedNode",
            "itemType": "node"
          },
          "text": "Failing Elements"
        }
      ],
      "items": [
        {
          "node": {
            "type": "node",
            "lhId": "9-196-SPAN",
            "path": "1,HTML,1,BODY,3,DIV,1,HEADER,4,LABEL,1,NAV,0,DIV,0,UL,0,LI,0,BUTTON,0,SPAN",
            "selector": "ul.usa-nav__primary > li.usa-nav__primary-item > button.usa-accordion__button > span",
            "boundingRect": {
              "top": 293,
              "bottom": 310,
              "left": 195,
              "right": 255,
              "width": 60,
              "height": 17
            },
            "snippet": "<span role=\"listitem\">",
            "nodeLabel": "About",
            "explanation": "Fix any of the following:\n  Required ARIA parents role not present: list, group"
          }
        },
        {
          "node": {
            "type": "node",
            "lhId": "9-197-SPAN",
            "path": "1,HTML,1,BODY,3,DIV,1,HEADER,4,LABEL,1,NAV,0,DIV,0,UL,1,LI,0,BUTTON,0,SPAN",
            "selector": "ul.usa-nav__primary > li.usa-nav__primary-item > button.usa-accordion__button > span",
            "boundingRect": {
              "top": 293,
              "bottom": 310,
              "left": 287,
              "right": 384,
              "width": 97,
              "height": 17
            },
            "snippet": "<span role=\"listitem\">",
            "nodeLabel": "Leadership",
            "explanation": "Fix any of the following:\n  Required ARIA parents role not present: list, group"
          }
        },
        {
          "node": {
            "type": "node",
            "lhId": "9-198-SPAN",
            "path": "1,HTML,1,BODY,3,DIV,1,HEADER,4,LABEL,1,NAV,0,DIV,0,UL,2,LI,0,BUTTON,0,SPAN",
            "selector": "ul.usa-nav__primary > li.usa-nav__primary-item > button.usa-accordion__button > span",
            "boundingRect": {
              "top": 293,
              "bottom": 310,
              "left": 416,
              "right": 473,
              "width": 57,
              "height": 17
            },
            "snippet": "<span role=\"listitem\">",
            "nodeLabel": "News",
            "explanation": "Fix any of the following:\n  Required ARIA parents role not present: list, group"
          }
        },
        {
          "node": {
            "type": "node",
            "lhId": "9-199-SPAN",
            "path": "1,HTML,1,BODY,3,DIV,1,HEADER,4,LABEL,1,NAV,0,DIV,0,UL,3,LI,0,BUTTON,0,SPAN",
            "selector": "ul.usa-nav__primary > li.usa-nav__primary-item > button.usa-accordion__button > span",
            "boundingRect": {
              "top": 293,
              "bottom": 310,
              "left": 505,
              "right": 628,
              "width": 123,
              "height": 17
            },
            "snippet": "<span role=\"listitem\">",
            "nodeLabel": "Export Control",
            "explanation": "Fix any of the following:\n  Required ARIA parents role not present: list, group"
          }
        },
        {
          "node": {
            "type": "node",
            "lhId": "9-200-SPAN",
            "path": "1,HTML,1,BODY,3,DIV,1,HEADER,4,LABEL,1,NAV,0,DIV,0,UL,4,LI,0,A,0,SPAN",
            "selector": "ul.usa-nav__primary > li.usa-nav__primary-item > a.usa-nav__link > span.no_menu_link_imaged__title",
            "boundingRect": {
              "top": 291,
              "bottom": 313,
              "left": 668,
              "right": 708,
              "width": 40,
              "height": 23
            },
            "snippet": "<span class=\"no_menu_link_imaged__title\" role=\"listitem\">",
            "nodeLabel": "FARA",
            "explanation": "Fix any of the following:\n  Required ARIA parents role not present: list, group"
          }
        },
        {
          "node": {
            "type": "node",
            "lhId": "9-201-SPAN",
            "path": "1,HTML,1,BODY,3,DIV,1,HEADER,4,LABEL,1,NAV,0,DIV,0,UL,5,LI,0,BUTTON,0,SPAN",
            "selector": "ul.usa-nav__primary > li.usa-nav__primary-item > button.usa-accordion__button > span",
            "boundingRect": {
              "top": 293,
              "bottom": 310,
              "left": 748,
              "right": 799,
              "width": 51,
              "height": 17
            },
            "snippet": "<span role=\"listitem\">",
            "nodeLabel": "FISA",
            "explanation": "Fix any of the following:\n  Required ARIA parents role not present: list, group"
          }
        },
        {
          "node": {
            "type": "node",
            "lhId": "9-202-SPAN",
            "path": "1,HTML,1,BODY,3,DIV,1,HEADER,4,LABEL,1,NAV,0,DIV,0,UL,6,LI,0,A,0,SPAN",
            "selector": "ul.usa-nav__primary > li.usa-nav__primary-item > a.usa-nav__link > span.no_menu_link_imaged__title",
            "boundingRect": {
              "top": 291,
              "bottom": 313,
              "left": 839,
              "right": 870,
              "width": 31,
              "height": 23
            },
            "snippet": "<span class=\"no_menu_link_imaged__title\" role=\"listitem\">",
            "nodeLabel": "OVT",
            "explanation": "Fix any of the following:\n  Required ARIA parents role not present: list, group"
          }
        }
      ],
      "debugData": {
        "type": "debugdata",
        "impact": "critical",
        "tags": [
          "cat.aria",
          "wcag2a",
          "wcag131"
        ]
      }
    },
    "errorCount": 7
  },
  {
    "id": "listitem",
    "title": "List items (`<li>`) are not contained within `<ul>` or `<ol>` parent elements.",
    "description": "Screen readers require list items (`<li>`) to be contained within a parent `<ul>` or `<ol>` to be announced properly. [Learn more](https://web.dev/listitem/).",
    "score": 0,
    "scoreDisplayMode": "binary",
    "details": {
      "type": "table",
      "headings": [
        {
          "key": "node",
          "itemType": "node",
          "subItemsHeading": {
            "key": "relatedNode",
            "itemType": "node"
          },
          "text": "Failing Elements"
        }
      ],
      "items": [
        {
          "node": {
            "type": "node",
            "lhId": "9-203-LI",
            "path": "1,HTML,1,BODY,3,DIV,1,HEADER,4,LABEL,1,NAV,0,DIV,0,UL,0,LI",
            "selector": "nav.usa-nav > div.usa-nav__inner > ul.usa-nav__primary > li.usa-nav__primary-item",
            "boundingRect": {
              "top": 267,
              "bottom": 337,
              "left": 179,
              "right": 271,
              "width": 92,
              "height": 71
            },
            "snippet": "<li class=\"usa-nav__primary-item\">",
            "nodeLabel": "About",
            "explanation": "Fix any of the following:\n  List item does not have a <ul>, <ol> parent element without a role, or a role=\"list\""
          }
        },
        {
          "node": {
            "type": "node",
            "lhId": "9-204-LI",
            "path": "1,HTML,1,BODY,3,DIV,1,HEADER,4,LABEL,1,NAV,0,DIV,0,UL,1,LI",
            "selector": "nav.usa-nav > div.usa-nav__inner > ul.usa-nav__primary > li.usa-nav__primary-item",
            "boundingRect": {
              "top": 267,
              "bottom": 337,
              "left": 271,
              "right": 400,
              "width": 129,
              "height": 71
            },
            "snippet": "<li class=\"usa-nav__primary-item\">",
            "nodeLabel": "Leadership",
            "explanation": "Fix any of the following:\n  List item does not have a <ul>, <ol> parent element without a role, or a role=\"list\""
          }
        },
        {
          "node": {
            "type": "node",
            "lhId": "9-205-LI",
            "path": "1,HTML,1,BODY,3,DIV,1,HEADER,4,LABEL,1,NAV,0,DIV,0,UL,2,LI",
            "selector": "nav.usa-nav > div.usa-nav__inner > ul.usa-nav__primary > li.usa-nav__primary-item",
            "boundingRect": {
              "top": 267,
              "bottom": 337,
              "left": 400,
              "right": 489,
              "width": 89,
              "height": 71
            },
            "snippet": "<li class=\"usa-nav__primary-item\">",
            "nodeLabel": "News",
            "explanation": "Fix any of the following:\n  List item does not have a <ul>, <ol> parent element without a role, or a role=\"list\""
          }
        },
        {
          "node": {
            "type": "node",
            "lhId": "9-206-LI",
            "path": "1,HTML,1,BODY,3,DIV,1,HEADER,4,LABEL,1,NAV,0,DIV,0,UL,3,LI",
            "selector": "nav.usa-nav > div.usa-nav__inner > ul.usa-nav__primary > li.usa-nav__primary-item",
            "boundingRect": {
              "top": 267,
              "bottom": 337,
              "left": 489,
              "right": 644,
              "width": 155,
              "height": 71
            },
            "snippet": "<li class=\"usa-nav__primary-item\">",
            "nodeLabel": "Export Control",
            "explanation": "Fix any of the following:\n  List item does not have a <ul>, <ol> parent element without a role, or a role=\"list\""
          }
        },
        {
          "node": {
            "type": "node",
            "lhId": "9-207-LI",
            "path": "1,HTML,1,BODY,3,DIV,1,HEADER,4,LABEL,1,NAV,0,DIV,0,UL,4,LI",
            "selector": "nav.usa-nav > div.usa-nav__inner > ul.usa-nav__primary > li.usa-nav__primary-item",
            "boundingRect": {
              "top": 267,
              "bottom": 337,
              "left": 644,
              "right": 732,
              "width": 88,
              "height": 71
            },
            "snippet": "<li class=\"usa-nav__primary-item\">",
            "nodeLabel": "FARA",
            "explanation": "Fix any of the following:\n  List item does not have a <ul>, <ol> parent element without a role, or a role=\"list\""
          }
        },
        {
          "node": {
            "type": "node",
            "lhId": "9-208-LI",
            "path": "1,HTML,1,BODY,3,DIV,1,HEADER,4,LABEL,1,NAV,0,DIV,0,UL,5,LI",
            "selector": "nav.usa-nav > div.usa-nav__inner > ul.usa-nav__primary > li.usa-nav__primary-item",
            "boundingRect": {
              "top": 267,
              "bottom": 337,
              "left": 732,
              "right": 815,
              "width": 83,
              "height": 71
            },
            "snippet": "<li class=\"usa-nav__primary-item\">",
            "nodeLabel": "FISA",
            "explanation": "Fix any of the following:\n  List item does not have a <ul>, <ol> parent element without a role, or a role=\"list\""
          }
        },
        {
          "node": {
            "type": "node",
            "lhId": "9-209-LI",
            "path": "1,HTML,1,BODY,3,DIV,1,HEADER,4,LABEL,1,NAV,0,DIV,0,UL,6,LI",
            "selector": "nav.usa-nav > div.usa-nav__inner > ul.usa-nav__primary > li.usa-nav__primary-item",
            "boundingRect": {
              "top": 267,
              "bottom": 337,
              "left": 815,
              "right": 894,
              "width": 79,
              "height": 71
            },
            "snippet": "<li class=\"usa-nav__primary-item\">",
            "nodeLabel": "OVT",
            "explanation": "Fix any of the following:\n  List item does not have a <ul>, <ol> parent element without a role, or a role=\"list\""
          }
        }
      ],
      "debugData": {
        "type": "debugdata",
        "impact": "serious",
        "tags": [
          "cat.structure",
          "wcag2a",
          "wcag131"
        ]
      }
    },
    "errorCount": 7
  }
]